mb_waves/__init__.py
mb_waves/cli/__init__.py
mb_waves/cli/helpers.py
mb_waves/cli/cmd/__init__.py
mb_waves/cli/cmd/generate_accounts_cmd.py
mb_waves/waves/__init__.py
mb_waves/waves/account.py
mb_waves/waves/helpers.py
mb_waves/waves/node_api.py
mb_waves-0.1.7.dist-info/METADATA
mb_waves-0.1.7.dist-info/WHEEL
mb_waves-0.1.7.dist-info/entry_points.txt
mb_waves-0.1.7.dist-info/top_level.txt
mb_waves-0.1.7.dist-info/RECORD
