Metadata-Version: 2.1
Name: mb-waves
Version: 0.1.7
Summary: UNKNOWN
License: UNKNOWN
Platform: UNKNOWN
Requires-Python: >=3.10
Requires-Dist: click (~=8.0.4)
Requires-Dist: click-aliases (~=1.0.1)
Requires-Dist: PyWaves (==0.8.42)
Requires-Dist: mb-std (~=0.3)
Provides-Extra: dev
Requires-Dist: pytest (==7.0.1) ; extra == 'dev'
Requires-Dist: pytest-xdist (==2.5.0) ; extra == 'dev'
Requires-Dist: pre-commit (==2.17.0) ; extra == 'dev'
Requires-Dist: wheel (==0.37.1) ; extra == 'dev'
Requires-Dist: twine (==3.8.0) ; extra == 'dev'
Requires-Dist: pip-audit (==2.0.0) ; extra == 'dev'
